MANIFEST.in
README.rst
setup.py
carrot/__init__.py
carrot/api.py
carrot/apps.py
carrot/consumer.py
carrot/exceptions.py
carrot/mocks.py
carrot/models.py
carrot/objects.py
carrot/scheduler.py
carrot/tests.py
carrot/urls.py
carrot/utilities.py
carrot/views.py
carrot/management/__init__.py
carrot/management/commands/__init__.py
carrot/management/commands/carrot.py
carrot/management/commands/carrot_daemon.py
carrot/management/commands/carrot_send.py
carrot/migrations/0001_initial.py
carrot/migrations/0002_add_task_name.py
carrot/migrations/0003_populate_task_name.py
carrot/migrations/0004_set_unique_task_name.py
carrot/migrations/__init__.py
carrot/static/carrot/axios.min.js
carrot/static/carrot/lodash.min.js
carrot/static/carrot/vue.min.js
carrot/static/carrot/vuetify.min.css
carrot/static/carrot/vuetify.min.js
carrot/static/carrot/vuex.min.js
carrot/static/carrot/white-carrot.png
carrot/templates/carrot/index.vue
django_carrot_dev.egg-info/PKG-INFO
django_carrot_dev.egg-info/SOURCES.txt
django_carrot_dev.egg-info/dependency_links.txt
django_carrot_dev.egg-info/requires.txt
django_carrot_dev.egg-info/top_level.txt
docs/__init__.py
docs/doc_settings.py
docs/source/__init__.py
docs/source/conf.py